elimity_insights_client/__init__.py
elimity_insights_client/_decode_domain_graph_schema.py
elimity_insights_client/_domain_graph_schema.py
elimity_insights_client/_elimity_insights_client.py
elimity_insights_client/_util.py
elimity_insights_client/api/__init__.py
elimity_insights_client/api/_api.py
elimity_insights_client/api/_decode_query_results_page.py
elimity_insights_client/api/_decode_source.py
elimity_insights_client/api/_encode_expression.py
elimity_insights_client/api/_encode_query.py
elimity_insights_client/api/entities/__init__.py
elimity_insights_client/api/entities/_entities.py
elimity_insights_client/api/entities/_entity.py
elimity_insights_client/api/entities/_parse_query_results_page.py
elimity_insights_client/api/entities/_query.py
elimity_insights_client/api/entities/_schema.py
elimity_insights_client/api/expression.py
elimity_insights_client/api/query.py
elimity_insights_client/api/query_results_page.py
elimity_insights_client/api/source.py
elimity_insights_client/csv.py
elimity_insights_client/py.typed
elimity_insights_client-10.2.1.dist-info/LICENSE.txt
elimity_insights_client-10.2.1.dist-info/WHEEL
elimity_insights_client-10.2.1.dist-info/METADATA
elimity_insights_client-10.2.1.dist-info/RECORD
