Metadata-Version: 2.1
Name: elimity-insights-client
Version: 10.2.1
Summary: Client for connector interactions with an Elimity Insights server
Home-page: https://github.com/elimity-com/insights-client-python
License: Apache-2.0
Author: Elimity development team
Author-email: dev@elimity.com
Requires-Python: >=3.7,<4.0
Classifier: License :: OSI Approved :: Apache Software License
Classifier: Programming Language :: Python :: 3
Classifier: Programming Language :: Python :: 3.7
Classifier: Programming Language :: Python :: 3.8
Classifier: Programming Language :: Python :: 3.9
Classifier: Programming Language :: Python :: 3.10
Classifier: Programming Language :: Python :: 3.11
Requires-Dist: more-itertools (>=8.14,<10.0)
Requires-Dist: python-dateutil (>=2.8.2,<3.0.0)
Requires-Dist: requests (>=2.28.1,<3.0.0)
Requires-Dist: simplejson (>=3.17.6,<4.0.0)
Requires-Dist: typing-extensions (>=4.3.0,<5.0.0)
Project-URL: Repository, https://github.com/elimity-com/insights-client-python
